pgk/__init__.py
pgk/essentials/__init__.py
pgk/essentials/basewidget.py
pgk/essentials/node.py
pgk/essentials/scene.py
pgk/essentials/scenes.py
pgk/essentials/widget.py
pgk/events/__init__.py
pgk/events/event.py
pgk/events/events.py
pgk/events/inputevent.py
pgk/events/keyboard.py
pgk/events/mouse.py
pgk/events/system.py
pgk/nodes/__init__.py
pgk/nodes/edittext.py
pgk/nodes/filledimage.py
pgk/nodes/image.py
pgk/nodes/renderableimage.py
pgk/nodes/sprite.py
pgk/nodes/text.py
pgk/nodes/textview.py
pgk/utils/__init__.py
pgk/utils/monitor.py
pgk/utils/position.py
pgk/utils/rect.py
pgk/utils/size.py
pgk/window/__init__.py
pgk/window/looptimer.py
pgk/window/program.py
pgk/window/window.py
pgk-0.1.3.dist-info/METADATA
pgk-0.1.3.dist-info/WHEEL
pgk-0.1.3.dist-info/top_level.txt
pgk-0.1.3.dist-info/RECORD
